{
  "url": null,
  "timestamp": "2015-12-07 00:37:54 +0100",
  "card": {
    "name": "export",
    "type": "Pointer",
    "content": "[[Metric+details+*type_plus_right+*structure]]\n[[Metric+*type+*structure]]\n[[Formula+details+*metric type plus right+*structure]]\n[[Metric+details+*type plus right]]\n[[formula metric item]]\n[[Formula+*metric type+*structure]]\n[[style: wikirate metrics]]\n[[Metric+right_sidebar+*type_plus_right+*structure]]\n[[input formula metric item]]\n[[add to formula]]\n[[homepage_company_item_2]]\n[[export]]\n[[production export]]",
    "value": [
      {
        "name": "Metric+details+*type plus right+*structure",
        "type": "HTML",
        "content": "<div class=\"row\">\r\n    \t\t\t\t\t   <div class=\"row-data titled-view\">\r\n    \t\t\t\t\t     <div class=\"card-header\">Contributing</div>\r\n    \t\t\t\t\t     {{_l+Value Policy|labeled;title:Value Policy|link}}\r\n    \t\t\t\t\t     {{_l+Projects|titled;title:Projects|link}}\r\n                </div>\r\n    \t\t\t\t\t\t  <div class=\"row-data\">\r\n                    {{_l+About|titled_with_edits;title:About;show:menu}}\r\n                  </div>\r\n                </div>"
      },
      {
        "name": "metric+*type+*structure",
        "type": "HTML",
        "content": "<div style=\"display: none\">{{+*metric type}}</div>\r\n\r\n<div class=\"container-fluid yinyang\">\r\n\t<div class=\"row wiki\">\r\n\t\t<div class=\"col-md-12 metric-info  \">\r\n\t\t  \r\n\t\t  <div class=\"row\">\r\n\t\t    <br>\r\n\t\t      <!--stuff on the right -->\r\n\t\t      <div class=\"col-md-4 pull-right nopadding\">\r\n          \t\t<div class=\"col-md-12 nopadding\">\r\n                  <div class=\"col-md-12 nopadding\">\r\n            \t\t\t\t<div class=\"col-md-2 nopadding\">\r\n            \t\t\t\t   <h5>Tags:</h5>\r\n            \t\t\t\t</div>\r\n            \t\t\t\t<div class=\"col-md-10 nopadding\">\r\n            \t\t\t\t  {{+topics|content|link}}\r\n            \t\t\t\t</div>\r\n                  </div>\r\n          \t\t\t\t<div class=\"col-md-4 nopadding\">\r\n          \t\t\t\t  <h5 class=\"pull-left\">Unit:</h5> <h5 class=\"pull-left\">{{+Unit|content}}</h5>\r\n          \t\t\t\t</div>\r\n          \t\t\t\t\r\n          \t\t\t\t<div class=\"col-md-4 nopadding\">\r\n          \t\t\t\t  <h5 class=\"pull-left\">Range:</h5> <h5 class=\"pull-left\">{{+Range|content}}</h5>\r\n          \t\t\t\t</div>\r\n          \t\t</div>\r\n          </div>\r\n          \r\n          \r\n\t\t      <!--Main title and stuff-->\r\n\t\t      <div class=\"col-md-8 metric-details-header\">\r\n  \t\t      <div class=\"row clearfix \">\r\n                <div class=\"col-md-1\">\r\n                  {{+*vote count}}\r\n                </div>  \r\n                <div class=\"col-md-11\">\r\n                  <div class=\"name row\">\r\n                    <a class=\"inherit-anchor\" href=\"{{_|linkname}}\">\r\n                    {{_r|name}}\r\n                    </a>\r\n                  </div>\r\n                  <div class=\"row\">\r\n                    <div class=\"metric-designer-info\">\r\n                      <a href=\"/{{_l|name}}+contribution\">\r\n                        <div><small class=\"text-muted\">Designed by</small></div>\r\n                        <div>{{_l+image|core;size:small}}</div>\r\n                        <div><h3>{{_l|name}}</h3></div>\r\n                      </a>\r\n                    </div>\r\n                  </div>\r\n                </div>\r\n            </div>\r\n          </div>\r\n        \r\n      </div>\r\n         <br>\r\n          <!--Question container-->\r\n\r\n      <div class=\"row question-container\">\r\n          <div class=\"row-icon\">\r\n            <i class=\"fa fa-question\"></i>\r\n          </div>\r\n          <div class=\"row-data\">\r\n            <small>Question</small>\r\n            {{+Question|content}}\r\n          </div>\r\n      </div>\r\n\t\t</div>\r\n\t</div>\r\n\t\r\n\t\r\n\t<div class=\"row metric-info\">\r\n\t \r\n\t <!--Ratings and company list -->\r\n\r\n\t\t<div class=\"col-md-6 rate border-right\">\r\n\t\t  <div class=\"row\">{{+right sidebar}}</div>\r\n\t\t</div>\r\n\t\t\r\n\t\t\r\n\t\t<!--Rightside -->\r\n\t\t\r\n\t\t<div class=\"col-md-6 wiki\">\r\n\t\t  \r\n\t\t  <!--tabs-->\r\n\r\n\t\t  <div class=\"tabbable\">\r\n\t\t\t\t<ul class=\"nav nav-tabs\">\r\n\t\t\t\t\t<li class=\"active\">\r\n\t\t\t\t\t\t<a href=\"#metric-details\" data-toggle=\"tab\"><h4>Details</h4></a>\r\n\t\t\t\t\t</li>\r\n\t\t\t\t\t<li>\r\n\t\t\t\t\t\t<a href=\"#metric-methodology\" data-toggle=\"tab\"><h4>Methodology</h4></a>\r\n\t\t\t\t\t</li>\r\n\t\t\t\t\t<li>\r\n\t\t\t\t\t\t<a href=\"#metric-references\" data-toggle=\"tab\"><h4>Sources</h4></a>\r\n\t\t\t\t\t</li>\r\n\t\t\t\t</ul>\r\n\t\t\t\t\r\n\t\t\t\t\r\n\t\t\t\t<div class=\"tab-content\">\r\n    \t\t\t\t\t<div class=\"tab-pane active\" id=\"metric-details\">\r\n    \t\t\t\t\t  {{+Details|core}}\r\n    \t\t\t\t\t</div>\r\n    \t\t\t\t\t\r\n    \t\t\t\t\t<div class=\"tab-pane\" id=\"metric-methodology\">\r\n    \t\t\t\t\t <div class=\"row\">\r\n            \t\t\t<div class=\"row-data\">\r\n                    {{+Unit|titled;title:Unit}}\r\n                  </div>\r\n                  <div class=\"row-data\">\r\n                    {{+Range|titled;title:Range}}\r\n                  </div>\r\n                  <div class=\"row-data\">\r\n                    {{+Methodology|titled;title:Methodology}}\r\n                  </div>   \r\n                </div> \r\n    \t\t\t\t\t</div>\r\n    \t\t\t\t\t\r\n    \t\t\t\t\t<div class=\"tab-pane \" id=\"metric-references\">\r\n                <div class=\"row\">\r\n                  <div class=\"row-icon\">\r\n                    <i class=\"fa fa-globe\"></i>\r\n                  </div>\r\n                  <div class=\"row-data\">\r\n                    {{+source|titled;title:Sources;|content;structure:source_item}}\r\n                  </div>\r\n                </div>\r\n    \t\t\t\t\t</div>\r\n\t\t\t\t</div>\r\n\t\t\t\t\r\n\t\t\t\t\r\n\t\t\t</div>\r\n\t\t\t\r\n\t\t\t<!-- discussion  -->\r\n\t\t\t<hr>\r\n\t\t\t<div class=\"row\">\r\n        <div class=\"row-icon\">\r\n          <i class=\"fa fa-comment\"></i>\r\n        </div>\r\n        <div class=\"row-data\">\r\n          {{+discussion|titled;title:Discussion; show:commentbox}}\r\n        </div>\r\n      </div>\r\n    \r\n    \r\n\t\t</div>\r\n\t</div>\r\n</div>\r\n\r\n"
      },
      {
        "name": "Formula+details+*metric type plus right+*structure",
        "type": "HTML",
        "content": "Test"
      },
      {
        "name": "Metric+details+*type plus right",
        "type": "Set"
      },
      {
        "name": "formula metric item",
        "type": "HTML",
        "content": "  <div class=\"yinyang-row\">\r\n  <!--prototype: Company+MetricDesigner+MetricName+yinyang drag item -->\r\n  <div class=\"metric-item value-item\">\r\n    <div class=\"header\">\r\n      <!--div class=\"hidden-xs hidden-md\">{{_lr+_r+*vote count}}</div-->\r\n      <a href=\"{{_lr+contributions|linkname}}\">\r\n      <div class=\"logo hidden-xs hidden-md\">\r\n        {{_lr+image|core;size:small}} \r\n      </div>\r\n      </a>\r\n      <div class=\"name\">\r\n        <a class=\"inherit-anchor\" href=\"{{_lr+_r|linkname}}\">\r\n          {{_r|name}}\r\n        </a>\r\n      </div>\r\n    </div>\r\n  </div>\r\n  </div>"
      },
      {
        "name": "Formula+*metric type+*structure",
        "type": "HTML",
        "content": "<div class=\"container-fluid yinyang\">\r\n\t<div class=\"row wiki\">\r\n\t\t<div class=\"col-md-12 metric-info  \">\r\n\t\t  \r\n\t\t  <div class=\"row\">\r\n\t\t    <br>\r\n\t\t      <!--stuff on the right -->\r\n\t\t      <div class=\"col-md-4 pull-right nopadding\">\r\n          \t\t<div class=\"col-md-12 nopadding\">\r\n          \t\t    <div class=\"col-md-12 nopadding\">\r\n          \t\t       <div class=\"col-md-3 nopadding\">\r\n            \t\t\t\t   <h5>Metric Type:</h5>\r\n            \t\t\t\t</div>\r\n            \t\t\t\t<div class=\"col-md-9 nopadding\">\r\n            \t\t\t\t  {{+*metric type|content|name}}\r\n            \t\t\t\t</div>\r\n          \t\t    </div>\r\n                  <div class=\"col-md-12 nopadding\">\r\n            \t\t\t\t<div class=\"col-md-3 nopadding\">\r\n            \t\t\t\t   <h5>Topics:</h5>\r\n            \t\t\t\t</div>\r\n            \t\t\t\t<div class=\"col-md-9 nopadding\">\r\n            \t\t\t\t  {{+topics|content|link}}\r\n            \t\t\t\t</div>\r\n                  </div>\r\n          \t\t</div>\r\n          </div>\r\n          \r\n          \r\n\t\t      <!--Main title and stuff-->\r\n\t\t      <div class=\"col-md-8 metric-details-header\">\r\n  \t\t      <div class=\"row clearfix \">\r\n                <div class=\"col-md-1\">\r\n                  {{+*vote count}}\r\n                </div>  \r\n                <div class=\"col-md-11\">\r\n                  <div class=\"name row\">\r\n                    <a class=\"inherit-anchor\" href=\"{{_|linkname}}\">\r\n                    {{_r|name}}\r\n                    </a>\r\n                  </div>\r\n                  <div class=\"row\">\r\n                    <div class=\"metric-designer-info\">\r\n                      <a href=\"/{{_l|name}}+contribution\">\r\n                        <div><small class=\"text-muted\">Designed by</small></div>\r\n                        <div>{{_l+image|core;size:small}}</div>\r\n                        <div><h3>{{_l|name}}</h3></div>\r\n                      </a>\r\n                    </div>\r\n                  </div>\r\n                </div>\r\n            </div>\r\n          </div>\r\n        \r\n      </div>\r\n         <br>\r\n          <!--Question container-->\r\n\r\n      <div class=\"row question-container\">\r\n          <div class=\"row-icon\">\r\n            <i class=\"fa fa-question\"></i>\r\n          </div>\r\n          <div class=\"row-data\">\r\n            <small>Question</small>\r\n            {{+Question|content}}\r\n          </div>\r\n      </div>\r\n\t\t</div>\r\n\t</div>\r\n\t\r\n\t\r\n\t<div class=\"row metric-info\">\r\n\t \r\n\t <!--Ratings and company list -->\r\n\r\n\t\t<div class=\"col-md-6 rate border-right\">\r\n\t\t  <div class=\"row\">{{+right sidebar}}</div>\r\n\t\t</div>\r\n\t\t\r\n\t\t\r\n\t\t<!--Rightside -->\r\n\t\t\r\n\t\t<div class=\"col-md-6 wiki\">\r\n\t\t  \r\n\t\t  <!--tabs-->\r\n\r\n\t\t  <div class=\"tabbable\">\r\n\t\t\t\t<ul class=\"nav nav-tabs\">\r\n\t\t\t\t\t<li class=\"active\">\r\n\t\t\t\t\t\t<a href=\"#metric-details\" data-toggle=\"tab\"><h4>Details</h4></a>\r\n\t\t\t\t\t</li>\r\n\t\t\t\t\t<li>\r\n\t\t\t\t\t\t<a href=\"#metric-references\" data-toggle=\"tab\"><h4>Sources</h4></a>\r\n\t\t\t\t\t</li>\r\n\t\t\t\t\t<li>\r\n\t\t\t\t\t\t<a href=\"#metric-discussion\" data-toggle=\"tab\"><h4>Discussion</h4></a>\r\n\t\t\t\t\t</li>\r\n\t\t\t\t</ul>\r\n\t\t\t\t\r\n\t\t\t\t\r\n\t\t\t\t<div class=\"tab-content\">\r\n    \t\t\t\t\t<div class=\"tab-pane active\" id=\"metric-details\">\r\n    \t\t\t\t\t  <div class=\"row\">\r\n    \t\t\t\t\t  {{+Formula|titled;title:Formula|name}}\r\n    \t\t\t\t\t  <div class=\"yinyang-list\">\r\n    \t\t\t\t\t  {{+Formula+*refers to|titled;title:Metrics used|content;structure:formula metric item}}\r\n                </div>    \t\t\t\r\n                <div class=\"row-data\">\r\n                    {{+Unit|titled;title:Unit}}\r\n                  </div>\r\n                  <div class=\"row-data\">\r\n                    {{+Range|titled;title:Range}}\r\n                  </div>\r\n                  <div class=\"col-md-4 nopadding\">\r\n          \t\t\t\t  <h5 class=\"pull-left\">Unit:</h5> <h5 class=\"pull-left\">{{+Unit|content}}</h5>\r\n          \t\t\t\t</div>\r\n          \t\t\t\t\r\n          \t\t\t\t<div class=\"col-md-4 nopadding\">\r\n          \t\t\t\t  <h5 class=\"pull-left\">Range:</h5> <h5 class=\"pull-left\">{{+Range|content}}</h5>\r\n          \t\t\t\t</div>\r\n                </div>\r\n    \t\t\t\t\t</div>\r\n    \t\t\t\t\t\r\n    \t\t\t\t\t<div class=\"tab-pane\" id=\"metric-discussion\">\r\n    \t\t\t\t\t <div class=\"row\">\r\n            \t\t\t<div class=\"row-icon\">\r\n                    <i class=\"fa fa-comment\"></i>\r\n                  </div>\r\n                  <div class=\"row-data\">\r\n                    {{+discussion|titled;title:Discussion; show:commentbox}}\r\n                  </div>  \r\n                </div> \r\n    \t\t\t\t\t</div>\r\n    \t\t\t\t\t\r\n    \t\t\t\t\t<div class=\"tab-pane \" id=\"metric-references\">\r\n                <div class=\"row\">\r\n                  <div class=\"row-icon\">\r\n                    <i class=\"fa fa-globe\"></i>\r\n                  </div>\r\n                  <div class=\"row-data\">\r\n                    {{+source|titled;title:Sources;|content;structure:source_item}}\r\n                  </div>\r\n                </div>\r\n    \t\t\t\t\t</div>\r\n\t\t\t\t</div>\r\n\t\t\t</div>\r\n\t\t</div>\r\n\t</div>\r\n</div>\r\n\r\n"
      },
      {
        "name": "style wikirate metrics",
        "type": "SCSS",
        "content": "$dark-text-color: #999;\r\n$bright-text-color: #ededed;\r\n\r\n$gray-background-color: #F3F3F3;\r\n\r\n$metric-color: #674ea7;\r\n$company-color: #d3741c;\r\n$topic-color: #2b7ea0;\r\n\r\n$company-header-bg: #d3741c;\r\n\r\n@mixin box-shadow($x: 2px, $y: 2px, $blur: 5px, $color: rgba(0,0,0,.4), $inset: \"\") {\r\n  @if ($inset != \"\") {\r\n    -webkit-box-shadow: $inset $x $y $blur $color;\r\n    -moz-box-shadow:    $inset $x $y $blur $color;\r\n    box-shadow:         $inset $x $y $blur $color;\r\n  } @else {\r\n    -webkit-box-shadow: $x $y $blur $color;\r\n    -moz-box-shadow:    $x $y $blur $color;\r\n    box-shadow:         $x $y $blur $color;\r\n  }\r\n}\r\n.height-auto{\r\n  height:auto!important;\r\n}\r\n.inherit-anchor{\r\n text-decoration: none;\r\n color:inherit!important;\r\n :hover{\r\n    text-decoration: none;\r\n    color:inherit;\r\n }\r\n}\r\n\r\n@mixin ellipsis() {\r\n  white-space: nowrap;\r\n  overflow: hidden;\r\n  text-overflow: ellipsis;\r\n}\r\n\r\n\r\n\r\n/*Common styles and classes*/\r\n\r\n.no-data-on-missing-view{\r\n  .missing-view a {\r\n      display: none;\r\n  }\r\n  \r\n   .missing-view:before {\r\n      content: \"\";\r\n      color: #F5BABA;\r\n      font-size:13px;\r\n  }\r\n}\r\n\r\n\r\n\r\n.company-header{\r\n  color: $company-color;\r\n  border-top: 3px solid $company-color;\r\n  font-size: 18px;\r\n  border-bottom: 1px solid $bright-text-color;\r\n  background: #FDFDFD;\r\n  padding: 2px 0px 0px 0px;\r\n}\r\n\r\n.topic-header{\r\n  color: $topic-color;\r\n  border-top: 3px solid $topic-color;\r\n  font-size: 14px;\r\n  border-bottom: 1px solid $bright-text-color;\r\n  padding: 2px 10px 5px 0px;\r\n  background: #FDFDFD;\r\n   @include ellipsis();\r\n}\r\n\r\n/*Common styles and classes ENDS*/\r\n\r\n.SELF-homepage_company{\r\n  .pointer-item{\r\n    float:left;\r\n  }\r\n  \r\n}\r\n\r\n.homepage-company-item{\r\n  max-width: 520px;\r\n  @include box-shadow(0,1px,6px,rgba(0,0,0,.13));\r\n  border: 1px solid $bright-text-color;\r\n  padding-bottom: 40px;\r\n  background-color: #fff;\r\n  .header-row {\r\n    font-size: 10px;\r\n    color: #bebebe;\r\n    text-align: center;\r\n    margin-top: 10px;\r\n    .header-header {\r\n      float: left;\r\n      margin-left: 80px;\r\n    }\r\n    .data-header {\r\n      width: 146px;\r\n      float: right;\r\n      margin-right: 15px;\r\n    }\r\n  }\r\n}\r\n.browse-company-item, .browse-topic-item{\r\n  width: 100%;\r\n}\r\n.browse-company-item, .browse-topic-item {\r\n  border: 1px solid $bright-text-color;\r\n  margin: 12px;\r\n  @include box-shadow(0,1px,6px,rgba(0,0,0,.13));\r\n  .company-content{\r\n    height: 281px;\r\n   .left{\r\n     \r\n   }\r\n   .right{\r\n     background: #f7f7f7;\r\n     height:100%;\r\n       overflow: hidden;// remove after limiting \r\n   }\r\n  }\r\n  .yinyang-row .value-item .header {\r\n    cursor: pointer;\r\n  }\r\n  .metric-column-title{\r\n      width: 100%;\r\n      float: left;\r\n      padding-top: 5px;\r\n      color: #B2B2B2;\r\n  }\r\n    .header-row {\r\n    font-size: 10px;\r\n    color: #bebebe;\r\n    text-align: center;\r\n    margin-top: 10px;\r\n    .header-header {\r\n      float: left;\r\n      margin-left: 80px;\r\n    }\r\n    .data-header {\r\n      width: 146px;\r\n      float: right;\r\n      margin-right: 15px;\r\n    }\r\n  }\r\n\r\n}\r\n\r\n.STRUCTURE-browse_company_item .company-header{\r\n   @include ellipsis();\r\n}\r\n\r\n.STRUCTURE-homepage_company_item,.STRUCTURE-browse_company_item, .STRUCTURE-browse_topic_item , .company-page-logo-container  {\r\n  .contribution-details{\r\n    display:none;\r\n    position: absolute;\r\n    width: 100%;\r\n    bottom: -107px;\r\n    .number-small {\r\n      border-right: 1px solid $bright-text-color;\r\n      border-bottom: 1px solid $bright-text-color;\r\n    }\r\n    a{\r\n      text-decoration:none;\r\n      &:hover{\r\n        text-decoration:none;\r\n      }\r\n    }\r\n    .row {\r\n      padding: 0;\r\n      margin: 0px;\r\n    }\r\n    .row > div {\r\n      padding: 0;\r\n      &:hover{\r\n        background:#fafafa;  \r\n      } \r\n    }\r\n  }\r\n  :hover .contribution-details{\r\n    display:block;\r\n  }\r\n  :hover .contribution-count{\r\n    display:none;\r\n  }\r\n}\r\n\r\n\r\n.center-logo{\r\n  border-right: 1px solid $bright-text-color;\r\n  >div {\r\n    height: 176px;\r\n    width: 100%;\r\n    overflow: hidden;\r\n    padding: 20px;\r\n    text-align: center;\r\n    }\r\n    .missing-view {\r\n      padding:0;\r\n      img {\r\n          width: 101%;\r\n          margin-left: -1px;\r\n      }\r\n    }\r\n    img{\r\n      position: relative;\r\n      top: 50%;\r\n      -webkit-transform: translateY(-50%);\r\n      -ms-transform: translateY(-50%);\r\n      transform: translateY(-50%);\r\n    }\r\n}\r\n\r\n\r\n.metric-source .tab-content {\r\n  background: #fffefa;\r\n  padding: 30px;\r\n}\r\n\r\n.form .metric-value-year {\r\n  width: 135px;\r\n}\r\n.form .metric-value-value {\r\n  width: 200px;\r\n}\r\n\r\n\r\n.label-metric {\r\n  background: $metric-color;\r\n  color: white;\r\n  a {\r\n    font-weight: normal;\r\n    color: white;\r\n  }\r\n}\r\n\r\n// metric value details\r\n.metric-year, .metric-unit {\r\n  font-size: 8px;\r\n  color: $dark-text-color;\r\n}\r\n.metric-value {\r\n  a {\r\n    color: #674ea7;\r\n  }\r\n  color: #674ea7;\r\n  font-size: 18px;\r\n  font-weight: bold;\r\n}\r\n.no-metric-value {\r\n  display: none;\r\n}\r\n\r\n\r\n.timeline {\r\n  &.container{\r\n    width:auto!important; //remove container class from the code\r\n    padding:0;\r\n  }\r\n  .year {\r\n    width: 35px; \r\n  }\r\n  .timeline-header {\r\n    .th {\r\n      float: left;\r\n      margin: 0px 10px 0px 10px;\r\n      font-weight: bold;\r\n      color:$dark-text-color;\r\n    }\r\n    .new a {\r\n      color: $dark-text-color;\r\n      background-color: $bright-text-color;\r\n      border: 1px solid #cdcdcd;\r\n      font-weight: normal;\r\n      font-size: 0.8em;\r\n      padding: 2px 5px 2px 5px;\r\n    }\r\n  }\r\n  .timeline-body {\r\n    width: 100%;\r\n    float: left;\r\n    .timeline-data {\r\n      width: 100%;\r\n      margin-left: -10px;\r\n     }\r\n    .metric-year, .metric-unit {\r\n      font-size: 12px;\r\n      }\r\n    .timeline-row {\r\n        position: relative;\r\n        clear: both;\r\n        padding: 7px 0px;\r\n        font-size: 12px;\r\n        width: 100%;\r\n        height: 45px;\r\n        color: $dark-text-color;\r\n      &:hover {\r\n        background-color: #F3F3F3;\r\n      }\r\n      .td {\r\n        float: left;\r\n        margin: 0px 10px 0px 10px;\r\n        .metric-value {\r\n          font-size: 20px;\r\n        }\r\n      }\r\n      .credit {\r\n        padding: 10px 5px;\r\n      }\r\n      .year {\r\n        padding: 8px 0px;\r\n      }\r\n      // .year, .credit {\r\n      //   padding-top: 2px;\r\n      // }\r\n      .search-result-list {\r\n        display: inline-block;\r\n        padding: 0px;\r\n        .search-result-item {\r\n          display: inline;\r\n          padding-left: 0;\r\n        }\r\n      }\r\n    }\r\n\r\n  }\r\n  .timeline-dot {\r\n    position: absolute;\r\n    top: 20px;\r\n    left: 46px;\r\n    height: 5px;\r\n    width: 5px;\r\n    background: gray;\r\n    z-index: 10;\r\n  }\r\n  .timeline-line {\r\n    position: absolute;\r\n    top: 21px;\r\n    left: 48px;\r\n    height: 53px;\r\n    width: 1px;\r\n    border-left: 1px solid #CCCCCC;\r\n    z-index: 9;\r\n  }\r\n}\r\n\r\n.RIGHT-company.card-content .company-item .item-link>a {\r\n  background: #03998d;\r\n  border-top-left-radius: 0px;\r\n  border-bottom-left-radius: 0px;\r\n}\r\n\r\n.metric-info, .metric-details-header, .metric-details-company-header {\r\n  .wiki .row {\r\n    margin-bottom: 18px;\r\n  }\r\n\r\n  .row {\r\n    margin-left: 5px;\r\n    margin-right: 5px;\r\n    .row-icon {\r\n      text-align: center;\r\n      font-size: 20px;\r\n      float: left;\r\n      color: $bright-text-color;\r\n      border: 1px solid $bright-text-color;\r\n      border-radius: 50%;\r\n      width: 35px;\r\n      height: 35px;\r\n      padding-top: 3px;\r\n    }\r\n    .glyphicon-question-mark {\r\n      font-weight: bold;\r\n    }\r\n    .row-data {\r\n      margin-left: 40px;\r\n    }\r\n  }\r\n}\r\n\r\n.metric-details-header {\r\n   .name{\r\n      font-size: 22px;\r\n      position: static;\r\n      color: $metric-color;\r\n   }\r\n   .metric-designer-info {\r\n     a {\r\n          color: inherit;\r\n      }\r\n     a>div {\r\n      float: left;\r\n      >small {\r\n          width: 65px;\r\n          display: inline-block;\r\n          text-align: right;\r\n          padding-top: 10px;\r\n          padding-right: 10px;\r\n      }\r\n\r\n     }\r\n      margin: 8px 0px;\r\n     img {\r\n        display: inline-block;\r\n        float: left;\r\n        max-height: 50px;\r\n        padding: 8px;\r\n        border: 1px solid #ebebeb;\r\n        margin: 0px 4px;\r\n    }\r\n    h3 {\r\n        margin: 10px 5px;\r\n        float: left;\r\n    }\r\n   }\r\n}\r\n\r\n.metric-details-question {\r\n  font-size: 18px;\r\n  padding: 5px 0px;\r\n}\r\n.metric-details-company-header {\r\n\r\n  .company-logo {\r\n    width: 100px;\r\n    float: left;\r\n    height: 100px;\r\n    border: 1px solid #ebebeb;\r\n    margin-left:10px;\r\n    .TYPE-image{\r\n      height:100px;\r\n      padding:4px;\r\n    }\r\n    img {\r\n       max-width: 100%;\r\n        max-height: 100px;\r\n        position: relative;\r\n        top: 50%;\r\n        -webkit-transform: translateY(-50%);\r\n        -ms-transform: translateY(-50%);\r\n        transform: translateY(-50%);\r\n    }\r\n\r\n  }\r\n  .company-name {\r\n    display: inline-block;\r\n    margin: 25px 10px;\r\n    font-size: 24px;\r\n    color:$company-header-bg;\r\n  }\r\n}\r\n.metric-details-close-icon  {\r\n    margin: 10px;\r\n    cursor: pointer;\r\n    position: absolute;\r\n    right: 0px;\r\n    z-index: 1;\r\n}\r\n\r\n.TYPE-metric_value {\r\n  .timeline, .RIGHT-discussion, .TYPE_PLUS_RIGHT-metric_value-source{\r\n    float: left;\r\n    width: 100%!important;\r\n    .missing-view{\r\n      display: none;\r\n    }\r\n  }\r\n}\r\n\r\n\r\n//browse metric\r\n.browse-metric-item {\r\n  padding: 0;\r\n  margin-bottom: 6px;\r\n  outline: 1px solid $bright-text-color;\r\n  border-top: 3px solid $metric-color;\r\n  @include box-shadow(0,1px,6px,rgba(0,0,0,.13));\r\n  font-size:14px;\r\n  .RIGHT-Xvote_count > div {\r\n    line-height: 1em;\r\n  }\r\n  button.vote-button {\r\n    color: $dark-text-color;\r\n    width: 15px;\r\n    height: 15px;\r\n    padding: 0;\r\n    border: none;\r\n    box-shadow: none;\r\n    --webkit-box-shadow: none;\r\n    background: none;\r\n  }\r\n  .vote-count {\r\n    color: $dark-text-color;\r\n    width: 15px;\r\n    height: 15px;\r\n  }\r\n  .logo {\r\n    padding-top: 5px;\r\n    float: left;\r\n    img {\r\n      max-width: 35px;\r\n      max-height: 35px;\r\n      margin: 0 10px;\r\n    }\r\n  }\r\n  .header {\r\n    margin: 4px 12px;\r\n  }\r\n  .name {\r\n    padding: 12px 16px;\r\n    font-size: 21px;\r\n    float: left;\r\n    max-width: 94%;\r\n    text-overflow: ellipsis;\r\n    white-space: nowrap;\r\n    overflow: hidden;\r\n    color: $metric-color;\r\n    a {\r\n      color: $metric-color; \r\n    }\r\n  }\r\n  .question {\r\n    height:60px;\r\n    text-overflow: ellipsis;\r\n    white-space: nowrap;\r\n    overflow: hidden;\r\n    color:$dark-text-color;\r\n }\r\n .topic{\r\n   height:38px;\r\n }\r\n}\r\n\r\n.data-count {\r\n  border-top: 1px solid $bright-text-color;\r\n  padding: 0;\r\n  text-align: center;\r\n  margin: 0px!important;\r\n  >div {\r\n      padding: 8px 0px;\r\n  }\r\n  > div:first-child {\r\n      border-right: 1px solid $bright-text-color;\r\n  }\r\n  .number-label {\r\n    font-size: 12px;\r\n    color: $dark-text-color;\r\n  }\r\n  .number {\r\n      font-size: 26px;\r\n  }\r\n  .number-small {\r\n      font-size: 14px;\r\n      padding:7px;\r\n  }\r\n  .number-large {\r\n        font-size: 26px;\r\n        height: 100px;\r\n        padding: 12%;\r\n  }\r\n}\r\n\r\n.ellipsis, .ellipsis .known-card {\r\n  max-width: 94%;\r\n  text-overflow: ellipsis;\r\n  white-space: nowrap;\r\n  overflow: hidden;\r\n}\r\n\r\n.SELF-metric .search-result-item.item-content {\r\n  width: 32%;\r\n  padding: 10px;\r\n  display: inline-block;\r\n  min-width: 350px;\r\n}\r\n\r\n.modal-body .LTYPE_RTYPE-metric-company .timeline {\r\n  padding-top: 10px;\r\n  margin-top: 25px;\r\n  border-top: 1px dotted $metric-color;\r\n  width: 100%;\r\n}\r\n\r\n.TYPE-metric.new-view form .form-group.RIGHT-Xvote_count {\r\n  display: none;\r\n}\r\n\r\n\r\nfieldset > .RIGHT-Xmetric_type ul.pointer-radio-list > li{\r\n  display: inline-block;\r\n  background-color: $gray-background-color;\r\n  padding: 10px;\r\n  \r\n}\r\n"
      },
      {
        "name": "Metric+right sidebar+*type plus right+*structure",
        "type": "HTML",
        "content": "<div class=\"col-md-12 text-center\">\r\n  <div class=\"btn-group\" role=\"group\" aria-label=\"...\">\r\n    <a class=\"btn btn-default slotter\"  href='/new/metric_value?layout=modal&slot[metric]={{_l|cgi_escape_name}}' data-toggle='modal' data-target='#modal-main-slot'>\r\n      <span class=\"fa fa-plus\"></span>\r\n      Add new value \r\n    </a>\r\n    \r\n    <a class=\"btn btn-default\" href='/new/source?layout=wikirate%20layout'>\r\n      <span class=\"fa fa-arrow-circle-o-down\"></span>\r\n      Import \r\n    </a>\r\n    \r\n    <a class=\"btn btn-default slotter\" href='/import_metric_values?layout=modal' data-toggle='modal' data-target='#modal-main-slot'>\r\n      Help <small>(how to)</small>\r\n    </a>\r\n</div>\r\n\r\n\r\n{{#year select|editor}}\r\n\r\n</div>\r\n\r\n<div class=\"col-md-12 form-horizontal\" style=\"display:none\">\r\n<div class=\"form-group\">\r\n<!-- show year once filter is done -->\r\n</div>\r\n</div>\r\n\r\n<div class=\"yinyang-list\">\r\n{{_left+all_values| hide:title;|content;structure:metric company item}}\r\n</div>\r\n    \r\n"
      },
      {
        "name": "input formula metric item",
        "type": "HTML",
        "content": "  <!--prototype: MetricDesigner+MetricName+yinyang drag item -->\r\n  <div class=\"metric-item value-item\">\r\n    <div class=\"header\">\r\n      <div class=\"handle\">\r\n        <span class=\"glyphicon glyphicon-option-vertical\"></span>\r\n      </div>\r\n      <div class=\"hidden-xs hidden-md\">{{_llr+_lr+*vote count}}</div>\r\n      <a href=\"{{_llr+contributions|linkname}}\">\r\n      <div class=\"logo hidden-xs hidden-md\">\r\n        {{_llr+image|core;size:small}} \r\n      </div>\r\n      </a>\r\n      <div class=\"name\">\r\n        <a class=\"inherit-anchor\" href=\"{{_llr+_lr|linkname}}\">\r\n          {{_lr|name}}\r\n        </a>\r\n      </div>\r\n    </div>\r\n    <div class=\"data metric-details-toggle\" data-append=\"metric_details_metric_header\">\r\n      <div class=\"data-item hide-with-details\">\r\n        {{_llr+_lr+_1+latest value|concise}}\r\n      </div>\r\n      <div class=\"data-item show-with-details text-center\">\r\n        <span class=\"label label-metric\">[[_llr+_lr|Metric Details]]</span> \r\n      </div>\r\n    </div>\r\n    <div class=\"details\">\r\n    </div>\r\n  </div>"
      },
      {
        "name": "add to formula",
        "type": "HTML",
        "content": "<div class=\"metric-details-close-icon pull-right\t\"><i class=\"fa fa-times-circle fa-2x\"></i></div>\r\n<br>\r\n<div class=\"metric-details-header\">\r\n  \r\n    <div class=\"row clearfix \">\r\n              <div class=\"col-md-11\">\r\n                <div class=\"name row\">\r\n                  <a class=\"inherit-anchor\" href=\"{{_self|url}}\">\r\n                  {{_r|name}}\r\n                  </a>\r\n                </div>\r\n                <div class=\"row\">\r\n                  <div class=\"metric-designer-info\">\r\n                    <a href=\"/{{_l|name}}+contribution\">\r\n                      <div><small class=\"text-muted\">Designed by</small></div>\r\n                      <div>{{_l+image|core;size:small}}</div>\r\n                      <div><h3>{{_l|name}}</h3></div>\r\n                    </a>\r\n                  </div>\r\n                </div>\r\n              </div>\r\n    </div>\r\n</div>",
        "codename": "add_to_formula"
      },
      {
        "name": "homepage company item 2",
        "type": "HTML",
        "content": "<div class=\"container homepage-company-item\">\r\n  <div class=\"row text-center company-header\">\r\n   <div class=\"col-md-3 col-xs-3 nopadding\">\r\n           <a class=\"inherit-anchor\" href=\"{{_|url}}\"><div class=\"row img-thumbnail homepage-logo-container\">{{_+image}}</div></a>\r\n   </div>\r\n  \r\n   <div class=\"col-md-9 col-xs-9\">\r\n        <div class=\"col-md-12 col-xs-12 text-left\">\r\n          <a class=\"inherit-anchor\" href=\"{{_|url}}\">\r\n            <h3>{{_|title}}</h3>\r\n          </a>\r\n          <br>\r\n        </div>\r\n        <div class=\"row contribution-details dark-grey-color remove-text-decoration\">\r\n          <div class=\"col-md-12 col-xs-12 data-count  clearfix\">\r\n            <div class=\"col-md-3 col-xs-3\">\r\n              <a class=\"inherit-anchor\" href=\"{{_|url}}\">\r\n                <div class=\"number-small\">{{_+metric+*cached count|core}}\r\n                  <div class=\"number-label\">Metrics</div>\r\n                </div> \r\n              </a>\r\n            </div>\r\n            <div class=\"col-md-3 col-xs-3 border-right\">\r\n              <a class=\"inherit-anchor\" href=\"{{_|url}}\">\r\n                <div class=\"number-small\">{{_+Analyses with Overviews+*cached count|core}}\r\n                  <div class=\"number-label\">Topics</div>\r\n                </div>\r\n              </a>\r\n            </div>\r\n            <div class=\"col-md-3 col-xs-3 border-right\">\r\n              <a class=\"inherit-anchor\" href=\"/notes?company={{_|linkname}}\">\r\n              <div class=\"number-small\">{{_+note+*cached count|core}}\r\n                <div class=\"number-label\">Notes</div>\r\n              </div>\r\n              </a>\r\n            </div>\r\n            <div class=\"col-md-3 col-xs-3 border-right\">\r\n              <a class=\"inherit-anchor\" href=\"/sources?company={{_|linkname}}\">\r\n              <div class=\"number-small\">{{_+source+*cached count|core}}\r\n                <div class=\"number-label\">Sources</div>\r\n              </div>\r\n              </a>\r\n            </div>\r\n          </div>\r\n        </div>\r\n     \r\n   </div>\r\n  \r\n  </div>\r\n  <div class=\"row clearfix company-content background-white \">\r\n    <div class=\"col-md-12 col-xs-12 \">\r\n      <div class=\"header-row\">\r\n        <div class=\"header-header\">\r\n          Metric\r\n        </div>\r\n        <div class=\"data-header\">\r\n          Value\r\n        </div>\r\n      </div>\r\n      {{_left+limited metric|yinyang list|content; structure:homepage company metric drag item}}\r\n    </div>\r\n  </div>\r\n\r\n</div>"
      },
      {
        "name": "export",
        "type": "Pointer",
        "content": "[[Metric+details+*type_plus_right+*structure]]\n[[Metric+*type+*structure]]\n[[Formula+details+*metric type plus right+*structure]]\n[[Metric+details+*type plus right]]\n[[formula metric item]]\n[[Formula+*metric type+*structure]]\n[[style: wikirate metrics]]\n[[Metric+right_sidebar+*type_plus_right+*structure]]\n[[input formula metric item]]\n[[add to formula]]\n[[homepage_company_item_2]]\n[[export]]\n[[production export]]"
      },
      {
        "name": "production export",
        "type": "Pointer",
        "content": "[[card with codename]]\n[[*ltype rtype+*right]]\n[[*ltype rtype+*right+*structure]]\n[[Metric+Company+*ltype rtype+*structure]]\n[[upvotee search+*right+*default]]\n[[novotee search+*right+*default]]\n[[cardtype+filter_search+*type_plu_right+*structure]]\n[[Topic+Company+*type plus right+*structure]]\n[[Topic+Company+*ltype rtype+*structure]]\n[[all card type]]\n[[*all+*style]]\n[[*all+*script]]\n[[home]]\n[[Source+*type+*autoname]]\n[[Apple Inc.]]\n[[Amazon.com, Inc.]]\n[[Amazon.com, Inc.+aliases]]\n[[Samsung]]\n[[Siemens AG]]\n[[Sony Corporation]]\n[[Natural Resource Use]]\n[[Community]]\n[[Human Rights]]\n[[Climate Change]]\n[[Animal Welfare]]\n[[Sebastian Jekutsch+CSR Report Available]]\n[[Good Company Index+Good Company Grade]]\n[[BSR+BSR Member]]\n[[Access to Nutrition Index+Marketing Score]]\n[[Year]]\n[[year+*type+by_update]]\n[[Metric+company+*type plus right+*structure]]\n[[loading gif]]\n[[creator credit]]\n[[Note+*type+*add help]]\n[[citation_count]]\n[[note+citation count+*type plus right]]\n[[note+citation count+*type plus right+*structure]]\n[[topic+*right+*default]]\n[[company+*right+*default]]\n[[missing image]]\n[[Metric value+source+*type plus right+*default]]\n[[Source+*type+*structure]]\n[[Metric value+*type+*structure]]\n[[metric company add value]]\n[[metric add value]]\n[[Company+*right+*default]]\n[[Year+*right+*default]]\n[[Metric value+value+*type plus right+*default]]\n[[Apple Inc.+Natural Resource Use]]\n[[Apple Inc.+Natural Resource Use+overview]]\n[[Samsung+Natural Resource Use]]\n[[Samsung+Natural Resource Use+overview]]\n[[*Vertical Logo]]\n[[company+limited metric+*type plus right+*structure]]\n[[yinyang drag item]]\n[[yinyang drag item+*right+*structure]]\n[[source+icon]]\n[[metric+icon]]\n[[overview+icon]]\n[[note+icon]]\n[[initiative+icon]]\n[[Company+contribution+*type plus right]]\n[[Company+contribution+*type plus right+*structure]]\n[[contribution+*right]]\n[[contribution+*right+*structure]]\n[[company+*type+*structure]]\n[[topic+*type+*structure]]\n[[analysis+*type+*structure]]\n[[related overviews+*right]]\n[[related overviews+*right+*structure]]\n[[cardtype+filter_search+*type_plu_right]]\n[[Note+*type+*structure]]\n[[Note+*self+*structure]]\n[[company+*right+*default]]\n[[note+company+*type plus right+*options]]\n[[Analysis+Overview+*type plus right]]\n[[Analysis+Overview+*type plus right+*add help]]\n[[Analysis+Overview+*type plus right+*help]]\n[[Cited Notes+*right]]\n[[Cited Notes+*right+*structure]]\n[[*count+*right+*structure]]\n[[Metric+values+*type plus right]]\n[[Metric+values+*type plus right+*structure]]\n[[metric values+*right]]\n[[metric values+*right+*structure]]\n[[contributed metrics+*right]]\n[[contributed metrics+*right+*structure]]\n[[contributed notes +*right]]\n[[contributed notes +*right+*structure]]\n[[contributed sources +*right]]\n[[contributed sources +*right+*structure]]\n[[contributed analysis +*right]]\n[[contributed analysis +*right+*structure]]\n[[contributed initiatives +*right]]\n[[contributed initiatives +*right+*structure]]\n[[initiatives edited by+*right]]\n[[initiatives edited by+*right+*structure]]\n[[venn icon]]\n[[CDP+Performance_Score]]\n[[CDP+Disclosure_Score]]\n[[CDP+Scope_2_Emissions]]\n[[CDP+Scope_2_Emissions+Apple_inc]]\n[[CDP+Disclosure_Score+Apple_inc]]\n[[CDP+Performance_Score+Apple_inc]]\n[[*vote count+*right]]\n[[*vote count+*right+*update]]\n[[novotee search+*right]]\n[[upvotee search+*right]]\n[[Topic+Company+*type plus right]]\n[[Topic+Company+*ltype rtype]]\n[[Analysis+Note+*type plus right]]\n[[Analysis+Note+*type plus right+*structure]]\n[[Analysis+Source+*type plus right]]\n[[Analysis+Source+*type plus right+*structure]]\n[[Metric+Company+*ltype rtype]]\n[[Metric+company+*type plus right+*structure]]\n[[Metric+company+*type plus right]]\n[[Metric+Company+*ltype rtype+*create]]\n[[Metric+Company+*ltype rtype+*update]]\n[[type search+*right+*default]]\n[[type search+*right]]\n[[downvotee search+*right]]\n[[downvotee search+*right+*default]]\n[[company+Metric+*type plus right]]\n[[company+Metric+*type plus right+*structure]]\n[[Company+Overview+*type plus right]]\n[[Company+Overview+*type plus right+*structure]]\n[[Company+Note+*type plus right]]\n[[Company+Note+*type plus right+*structure]]\n[[Company+Sources+*type plus right]]\n[[Company+Sources+*type plus right+*structure]]\n[[Uncited Notes]]\n[[Uncited Notes+*right]]\n[[Uncited Notes+*right+*structure]]\n[[Cited Notes+*right+*structure]]\n[[Analysis+Note+*type plus right+*structure]]\n[[source item]]\n[[Note+Source+*type plus right+*default]]\n[[Note+Source+*type plus right+*structure]]\n[[source link]]\n[[source icon3]]\n[[metric+right sidebar+*type plus right+*structure]]\n[[metric+*type+*structure]]\n[[Metric_value+year+*type_plus_right+*input]]\n[[Metric value+company+*type plus right+*input]]\n[[year+*right+*options]]\n[[company+*right+*options]]\n[[Metric+companies with value+*type plus right+*structure]]\n[[metric company item]]\n[[Company+right sidebar+*type plus right+*structure]]\n[[Company+metric sidebar+*type plus right+*structure]]\n[[company metric drag item]]\n[[latest value+*right+*structure]]\n[[nav bar menu]]\n[[all values]]\n[[Source+File+*type plus right]]\n[[Source+File+*type plus right+*default]]\n[[Source+Title+*type plus right]]\n[[Source+Title+*type plus right+*default]]\n[[Source+Link+*type plus right]]\n[[Link+*right+*default]]\n[[Initiative+Participants+*type plus right+*structure]]\n[[*metric type+*right+*default]]\n[[*metric type+*right+*input]]\n[[*metric type+*right+*options]]\n[[*metric type plus right+*right+*structure]]\n[[Metric type+*metric type+*type plus right+*structure]]\n[[Metric type]]"
      }
    ]
  }
}