{
  "url": null,
  "timestamp": "2016-04-28 03:57:20 +0100",
  "card": {
    "name": "export",
    "type": "Pointer",
    "content": "[[export]]\n[[Metric Value+checked by+*type plus right+*default]]\n[[checked by]]",
    "value": [
      {
        "name": "export",
        "type": "Pointer",
        "content": "[[export]]\n[[Metric Value+checked by+*type plus right+*default]]\n[[checked by]]"
      },
      {
        "name": "Metric value+checked by+*type plus right+*default",
        "type": "Pointer",
        "content": ""
      },
      {
        "name": "checked by",
        "type": "Basic",
        "content": "",
        "codename": "checked_by"
      }
    ]
  }
}